{
  "id": "http://localhost:8888/content/vertebra/index.json",
  "type": "Manifest",
  "label": "Vertebra",
  "sequences": [
    {
      "type": "Sequence",
      "canvases": [
        {
          "id": "http://localhost:8888/content/vertebra/index.json/canvas/0",
          "type": "Canvas",
          "content": [
            {
              "id": "http://localhost:8888/content/vertebra/index.json/canvas/0/annotationpage/0",
              "type": "AnnotationPage",
              "items": [
                {
                  "id": "http://localhost:8888/content/vertebra/index.json/canvas/0/annotation/0",
                  "type": "Annotation",
                  "motivation": "painting",
                  "body": {
                    "id": "http://localhost:8888/content/vertebra/_vertebra/hc941fm6529.obj",
                    "type": "PhysicalObject",
                    "format": "text/plain",
                    "label": "_vertebra"
                  },
                  "target": "http://localhost:8888/content/vertebra/index.json/canvas/0"
                }
              ]
            }
          ],
          "label": "_vertebra"
        }
      ]
    }
  ],
  "attribution": "Stanford",
  "thumbnail": [
    {
      "id": "http://localhost:8888/content/vertebra/thumb.jpg",
      "type": "Image"
    }
  ]
}